LICENSE
MANIFEST.in
README.md
README.rst
requirements.txt
setup.py
datahub/__init__.py
datahub/core.py
datahub/exceptions.py
datahub/implement.py
datahub/rest.py
datahub/version.py
datahub/auth/__init__.py
datahub/auth/aliyun_account.py
datahub/auth/core.py
datahub/batch/__init__.py
datahub/batch/batch_binary_record.py
datahub/batch/batch_header.py
datahub/batch/batch_serializer.py
datahub/batch/binary_record.py
datahub/batch/record_header.py
datahub/batch/schema_registry_client.py
datahub/batch/utils.py
datahub/client/__init__.py
datahub/client/common/__init__.py
datahub/client/common/config.py
datahub/client/common/constant.py
datahub/client/common/datahub_factory.py
datahub/client/common/library_factory.py
datahub/client/common/meta_data.py
datahub/client/common/offset_meta.py
datahub/client/common/shard_coordinator.py
datahub/client/common/thread_pool.py
datahub/client/common/timer.py
datahub/client/consumer/__init__.py
datahub/client/consumer/consumer_coordinator.py
datahub/client/consumer/consumer_heartbeat.py
datahub/client/consumer/datahub_consumer.py
datahub/client/consumer/message_key.py
datahub/client/consumer/message_reader.py
datahub/client/consumer/offset_coordinator.py
datahub/client/consumer/offset_manager.py
datahub/client/consumer/offset_select_strategy.py
datahub/client/consumer/shard_group_reader.py
datahub/client/consumer/shard_reader.py
datahub/client/consumer/sync_group_meta.py
datahub/client/producer/__init__.py
datahub/client/producer/datahub_producer.py
datahub/client/producer/message_writer.py
datahub/client/producer/record_pack.py
datahub/client/producer/record_pack_queue.py
datahub/client/producer/shard_group_writer.py
datahub/client/producer/shard_writer.py
datahub/client/producer/write_result.py
datahub/models/__init__.py
datahub/models/compress.py
datahub/models/connector.py
datahub/models/cursor.py
datahub/models/params.py
datahub/models/record.py
datahub/models/results.py
datahub/models/schema.py
datahub/models/shard.py
pydatahub.egg-info/PKG-INFO
pydatahub.egg-info/SOURCES.txt
pydatahub.egg-info/dependency_links.txt
pydatahub.egg-info/requires.txt
pydatahub.egg-info/top_level.txt