Metadata-Version: 2.4
Name: pydatahub
Version: 2.25.8
Summary: Datahub Python SDK
Home-page: https://github.com/aliyun/aliyun-datahub-sdk-python
Author: panjinxing.pjx
Author-email: panjinxing.pjx@alibaba-inc.com
License: Apache License 2.0
Keywords: pydatahub,python,aliyun,datahub,sdk
License-File: LICENSE
Requires-Dist: funcsigs>=1.0.2
Requires-Dist: requests>=2.4.0
Requires-Dist: simplejson>=3.3.0
Requires-Dist: six>=1.1.0
Requires-Dist: enum34>=1.1.5; python_version < "3.4"
Requires-Dist: crcmod>=1.7
Requires-Dist: lz4>=2.0.0
Requires-Dist: cprotobuf>=0.1.9
Requires-Dist: atomic>=0.7.0
Requires-Dist: rwlock>=0.0.6
Requires-Dist: urllib3>=1.26.10
Dynamic: author
Dynamic: author-email
Dynamic: description
Dynamic: home-page
Dynamic: keywords
Dynamic: license
Dynamic: license-file
Dynamic: requires-dist
Dynamic: summary
